ecs_scaling_scheduler/__init__.py
ecs_scaling_scheduler/aws_lambda_functions/__init__.py
ecs_scaling_scheduler/ecs_scaling_scheduler.py
ecs_scaling_scheduler-0.1.0.dist-info/LICENSE
ecs_scaling_scheduler-0.1.0.dist-info/WHEEL
ecs_scaling_scheduler-0.1.0.dist-info/METADATA
ecs_scaling_scheduler-0.1.0.dist-info/RECORD
