Metadata-Version: 2.1
Name: ecs-scaling-scheduler
Version: 0.1.0
Summary: Functions triggered on events to manage ECS Services scaling activities
License: MPL-2.0
Author: johnpreston
Author-email: john@compose-x.io
Requires-Python: >=3.7,<4.0
Classifier: License :: OSI Approved
Classifier: Natural Language :: English
Classifier: Programming Language :: Python :: 3
Classifier: Programming Language :: Python :: 3.10
Classifier: Programming Language :: Python :: 3.7
Classifier: Programming Language :: Python :: 3.8
Classifier: Programming Language :: Python :: 3.9
Requires-Dist: boto3 (>=1.21,<2.0)
Requires-Dist: compose-x-common (>=0.4.4,<0.5.0)
